tiobeindexpy/__init__.py
tiobeindexpy/tiobeindexpy.py
tiobeindexpy-1.0.0.dist-info/METADATA
tiobeindexpy-1.0.0.dist-info/RECORD
tiobeindexpy-1.0.0.dist-info/WHEEL
tiobeindexpy-1.0.0.dist-info/top_level.txt
