Metadata-Version: 2.1
Name: tiobeindexpy
Version: 1.0.0
Summary: A Python package for getting TIOBE Index
Home-page: https://github.com/amrrs/tiobeindexpy
Author: AbdulMajedRaja RS
Author-email: amrrs.data@gmail.com
License: MIT
Keywords: tiobe,programming language ranking,index,programming language
Platform: UNKNOWN
Requires-Dist: requests
Requires-Dist: beautifulsoup4
Requires-Dist: pandas
